Workbook

Sheet 说明
B2: T4 埋错狩猎 · 标准件 · 经营毛利模型查错挑战
B4: 这份工作簿是什么
B5: 某标准件产品线 2026 年 1-12 月的管理层损益模型，含 月度数据 / 毛利分析 / 费用分析 / 预算对比 / 校验 五张表。
B6: 全部为合成模拟数据（随机种子 20261201）。「校验」表 12 项检查中，一部分按设计为 FALSE。
B8: 挑战
B9: 模型公式中埋了 8 处隐蔽错误：求和范围差一行、引用列错位、方向写反、
B10: 分子分母颠倒、统计口径用反等典型真实错误，无一处会产生 #DIV/0! 之类显性报错。
B11: 任务是：把 8 处错误全部定位到具体单元格，并给出正确公式。
B12: 注意：校验表是有用的，但它本身未必覆盖所有错误。
B14: 约定
B15: 蓝色=硬输入（含来源批注），黑色=本表公式，绿色=跨表链接。
B16: 金额单位：元；比率单位：%。合成模拟数据 [测算]。

Sheet 月度数据
A4: 月份 | B4: 销量 | C4: 单价 | D4: 收入 | E4: 原材料 | F4: 人工 | G4: 制造费用 | H4: 运输费用 | I4: 销售费用 | J4: 管理费用
A5: 1 | B5: 2361 | C5: 405.9 | D5: 958329.9 | E5: 467843.15 | F5: 128637.65 | G5: 134619.82 | H5: 50452.06 | I5: 75387.48 | J5: 113994.84
A6: 2 | B6: 3241 | C6: 411.87 | D6: 1334870.7 | E6: 589992.97 | F6: 212382.58 | G6: 185778.77 | H6: 74570.09 | I6: 80849.3 | J6: 87256.1
A7: 3 | B7: 2419 | C7: 318.67 | D7: 770862.73 | E7: 337578.85 | F7: 102120.32 | G7: 109278.74 | H7: 38875.47 | I7: 65705.81 | J7: 89620.23
A8: 4 | B8: 3113 | C8: 91.58 | D8: 285088.54 | E8: 121639.42 | F8: 56127.01 | G8: 33655.52 | H8: 15343.18 | I8: 20681.89 | J8: 29149.81
A9: 5 | B9: 2782 | C9: 386.29 | D9: 1074658.8 | E9: 464875.29 | F9: 183314.94 | G9: 95576.88 | H9: 55142.97 | I9: 67340.15 | J9: 106940.62
A10: 6 | B10: 2552 | C10: 419.95 | D10: 1071712.4 | E10: 379525.32 | F10: 156318.83 | G10: 159697.22 | H10: 42559.01 | I10: 63070.73 | J10: 118690.07
A11: 7 | B11: 1753 | C11: 310.38 | D11: 544096.14 | E11: 250077.08 | F11: 93879.34 | G11: 54372.5 | H11: 19503.16 | I11: 32744.03 | J11: 48516.44
A12: 8 | B12: 1898 | C12: 461.84 | D12: 876572.32 | E12: 347762.08 | F12: 166151.95 | G12: 98623.06 | H12: 29000.92 | I12: 65180.03 | J12: 91385.21
A13: 9 | B13: 3080 | C13: 191.66 | D13: 590312.8 | E13: 283105.13 | F13: 80758.15 | G13: 49109.46 | H13: 30219.33 | I13: 30189.93 | J13: 40359.67
A14: 10 | B14: 2349 | C14: 287.74 | D14: 675901.26 | E14: 326680.64 | F14: 90408.44 | G14: 68939.68 | H14: 31899.98 | I14: 40399.2 | J14: 76687.24
A15: 11 | B15: 3840 | C15: 412.24 | D15: 1583001.6 | E15: 562244.91 | F15: 273188.29 | G15: 195384.49 | H15: 68541.69 | I15: 138263.59 | J15: 117506.71
A16: 12 | B16: 1513 | C16: 158.36 | D16: 239598.68 | E16: 106210.25 | F16: 41257.41 | G16: 20484.26 | H16: 9022.21 | I16: 20067.96 | J16: 15751.22

Sheet 毛利分析
A4: 月份 | B4: 收入 | C4: 变动成本 | D4: 毛利 | E4: 毛利率 | F4: 单位毛利 | G4: 单位成本 | H4: 累计毛利率 | I4: 收入环比 | J4: 累计收入 | K4: 累计毛利 | L4: 占全年收入
A5: 1 | B5: =月度数据!D5 -> 958329.9 | C5: =月度数据!E5+月度数据!F5+月度数据!G5+月度数据!H5 -> 781552.68 | D5: =B5-C5 -> 176777.22 | E5: =D5/B5 -> 0.18446385 | F5: =D5/月度数据!B5 -> 74.873875 | G5: =C5/月度数据!B5 -> 331.02612 | H5: - | J5: =SUM(B5:B$6) -> 2293200.6 | K5: 0 | L5: =D5/$B$17 -> 0.017668877
A6: 2 | B6: =月度数据!D6 -> 1334870.7 | C6: =月度数据!E6+月度数据!F6+月度数据!G6+月度数据!H6 -> 1062724.4 | D6: =B6-C6 -> 272146.26 | E6: =D6/B6 -> 0.20387463 | F6: =D6/月度数据!B6 -> 83.969843 | G6: =C6/月度数据!B6 -> 327.90016 | H6: =SUM(D$5:D5)/SUM(B$5:B6) -> 0.077087553 | I6: =B7/B6-1 -> -0.42251879 | J6: =SUM(B$6:B6) -> 1334870.7 | K6: =SUM(D$5:D5) -> 176777.22 | L6: =D6/$B$17 -> 0.02720101
A7: 3 | B7: =月度数据!D7 -> 770862.73 | C7: =月度数据!E7+月度数据!F7+月度数据!G7+月度数据!H7 -> 587853.38 | D7: =B7-C7 -> 183009.35 | E7: =D7/B7 -> 0.23740848 | F7: =D7/月度数据!B7 -> 75.654961 | G7: =C7/月度数据!B7 -> 243.01504 | H7: =SUM(D$5:D6)/SUM(B$5:B7) -> 0.14651247 | I7: =B7/B6-1 -> -0.42251879 | J7: =SUM(B$6:B7) -> 2105733.4 | K7: =SUM(D$5:D6) -> 448923.48 | L7: =D7/$B$17 -> 0.018291778
A8: 4 | B8: =月度数据!D8 -> 285088.54 | C8: =月度数据!E8+月度数据!F8+月度数据!G8+月度数据!H8 -> 226765.13 | D8: =B8-C8 -> 58323.41 | E8: =D8/B8 -> 0.20457999 | F8: =D8/月度数据!B8 -> 18.735435 | G8: =C8/月度数据!B8 -> 72.844565 | H8: =SUM(D$5:D7)/SUM(B$5:B8) -> 0.18868444 | I8: =B8/B7-1 -> -0.63016951 | J8: =SUM(B$6:B8) -> 2390821.9 | K8: =SUM(D$5:D7) -> 631932.83 | L8: =D8/$B$17 -> 0.0058294229
A9: 5 | B9: =月度数据!D9 -> 1074658.8 | C9: =月度数据!E9+月度数据!F9+月度数据!G9+月度数据!H9 -> 798910.08 | D9: =B9-C9 -> 275748.7 | E9: =D9/B9 -> 0.25659186 | F9: =D9/月度数据!B9 -> 99.118871 | G9: =C9/月度数据!B9 -> 287.17113 | H9: =SUM(D$5:D8)/SUM(B$5:B9) -> 0.15603205 | I9: =B9/B8-1 -> 2.7695615 | J9: =SUM(B$6:B9) -> 3465480.7 | K9: =SUM(D$5:D8) -> 690256.24 | L9: =D9/$B$17 -> 0.027561073
A10: 6 | B10: =月度数据!D10 -> 1071712.4 | C10: =月度数据!E10+月度数据!F10+月度数据!G10+月度数据!H10 -> 738100.38 | D10: =B10-C10 -> 333612.02 | E10: =D10/B10 -> 0.31128876 | F10: =D10/月度数据!B10 -> 130.72571 | G10: =C10/月度数据!B10 -> 289.22429 | H10: =SUM(D$5:D9)/SUM(B$5:B10) -> 0.17578035 | I10: =B10/B9-1 -> -0.0027416889 | J10: =SUM(B$6:B10) -> 4537193.1 | K10: =SUM(D$5:D9) -> 966004.94 | L10: =D10/$B$17 -> 0.03334451
A11: 7 | B11: =月度数据!D11 -> 544096.14 | C11: =月度数据!E11+月度数据!F11+月度数据!G11+月度数据!H11 -> 417832.08 | D11: =B11-C11 -> 126264.06 | E11: =D11/B11 -> 0.23206204 | F11: =D11/月度数据!B11 -> 72.027416 | G11: =C11/月度数据!B11 -> 238.35258 | H11: =SUM(D$5:D10)/SUM(B$5:B11) -> 0.21518194 | I11: =B11/B10-1 -> -0.49231143 | J11: =SUM(B$6:B11) -> 5081289.3 | K11: =SUM(D$5:D10) -> 1299617 | L11: =D11/$B$17 -> 0.012620089
A12: 8 | B12: =月度数据!D12 -> 876572.32 | C12: =月度数据!E12+月度数据!F12+月度数据!G12+月度数据!H12 -> 641538.01 | D12: =B12-C12 -> 235034.31 | E12: =D12/B12 -> 0.26812883 | F12: =D12/月度数据!B12 -> 123.83262 | G12: =C12/月度数据!B12 -> 338.00738 | H12: =SUM(D$5:D11)/SUM(B$5:B12) -> 0.20616564 | I12: =B12/B11-1 -> 0.61106146 | J12: =SUM(B$6:B12) -> 5957861.6 | K12: =SUM(D$5:D11) -> 1425881 | L12: =D12/$B$17 -> 0.023491671
A13: 9 | B13: =月度数据!D13 -> 590312.8 | C13: =月度数据!E13+月度数据!F13+月度数据!G13+月度数据!H13 -> 443192.07 | D13: =B13-C13 -> 147120.73 | E13: =D13/B13 -> 0.24922504 | F13: =D13/月度数据!B13 -> 47.766471 | G13: =C13/月度数据!B13 -> 143.89353 | H13: =SUM(D$5:D12)/SUM(B$5:B13) -> 0.22126349 | I13: =B13/B12-1 -> -0.32656692 | J13: =SUM(B$6:B13) -> 6548174.4 | K13: =SUM(D$5:D12) -> 1660915.3 | L13: =D13/$B$17 -> 0.014704712
A14: 10 | B14: =月度数据!D14 -> 675901.26 | C14: =月度数据!E14+月度数据!F14+月度数据!G14+月度数据!H14 -> 517928.74 | D14: =B14-C14 -> 157972.52 | E14: =D14/B14 -> 0.2337213 | F14: =D14/月度数据!B14 -> 67.250966 | G14: =C14/月度数据!B14 -> 220.48903 | H14: =SUM(D$5:D13)/SUM(B$5:B14) -> 0.22096632 | I14: =B14/B13-1 -> 0.14498832 | J14: =SUM(B$6:B14) -> 7224075.6 | K14: =SUM(D$5:D13) -> 1808036.1 | L14: =D14/$B$17 -> 0.015789348
A15: 11 | B15: =月度数据!D15 -> 1583001.6 | C15: =月度数据!E15+月度数据!F15+月度数据!G15+月度数据!H15 -> 1099359.4 | D15: =B15-C15 -> 483642.22 | E15: =D15/B15 -> 0.30552226 | F15: =D15/月度数据!B15 -> 125.94849 | G15: =C15/月度数据!B15 -> 286.29151 | H15: =SUM(D$5:D14)/SUM(B$5:B15) -> 0.20132377 | I15: =B15/B14-1 -> 1.3420604 | J15: =SUM(B$6:B15) -> 8807077.2 | K15: =SUM(D$5:D14) -> 1966008.6 | L15: =D15/$B$17 -> 0.048340024
A16: 12 | B16: =月度数据!D16 -> 239598.68 | C16: =月度数据!E16+月度数据!F16+月度数据!G16+月度数据!H16 -> 176974.13 | D16: =B16-C16 -> 62624.55 | E16: =D16/B16 -> 0.26137268 | F16: =D16/月度数据!B16 -> 41.390978 | G16: =C16/月度数据!B16 -> 116.96902 | H16: =SUM(D$5:D15)/SUM(B$5:B16) -> 0.24484252 | I16: =B16/B15-1 -> -0.84864281 | J16: =SUM(B$6:B16) -> 9046675.9 | K16: =SUM(D$5:D15) -> 2449650.8 | L16: =D16/$B$17 -> 0.0062593217
A17: 合计/全年 | B17: =SUM(B5:B16) -> 10005006 | C17: =SUM(C5:C16) -> 7492730.5 | D17: =SUM(D5:D16) -> 2512275.4 | E17: =D17/B17 -> 0.25110184 | F17: =D17/SUM(月度数据!B5:B16) -> 81.300778 | G17: =C16/SUM(月度数据!B5:B16) -> 5.7271328 | L17: =SUM(L5:L16) -> 0.25110184

Sheet 费用分析
A4: 月份 | B4: 销售费用 | C4: 管理费用 | D4: 运输费用 | E4: 费用合计 | F4: 销售费用率 | G4: 管理费用率 | H4: 总费用率 | I4: 费用环比 | J4: 累计费用
A5: 1 | B5: =月度数据!I5 -> 75387.48 | C5: =月度数据!J5 -> 113994.84 | D5: =月度数据!H5 -> 50452.06 | E5: =B5+C5+D5 -> 239834.38 | F5: =B5/毛利分析!B5 -> 0.078665478 | G5: =C5/毛利分析!B5 -> 0.11895156 | H5: =E5/毛利分析!B5 -> 0.25026286 | J5: =SUM(E$5:E5) -> 239834.38
A6: 2 | B6: =月度数据!I6 -> 80849.3 | C6: =月度数据!J6 -> 87256.1 | D6: =月度数据!H6 -> 74570.09 | E6: =B6+C6+D6 -> 242675.49 | F6: =B6/毛利分析!B6 -> 0.060567141 | G6: =C6/毛利分析!B6 -> 0.065366707 | H6: =E6/毛利分析!B6 -> 0.18179701 | I6: =E6/E5-1 -> 0.011846133 | J6: =SUM(E$5:E6) -> 482509.87
A7: 3 | B7: =月度数据!I7 -> 65705.81 | C7: =月度数据!J7 -> 89620.23 | D7: =月度数据!H7 -> 38875.47 | E7: =B7+C7+D7 -> 194201.51 | F7: =B7/毛利分析!B7 -> 0.085236719 | G7: =C7/毛利分析!B7 -> 0.11625965 | H7: =E7/毛利分析!B7 -> 0.25192749 | I7: =E7/E6-1 -> -0.19974815 | J7: =SUM(E$5:E7) -> 676711.38
A8: 4 | B8: =月度数据!I8 -> 20681.89 | C8: =月度数据!J8 -> 29149.81 | D8: =月度数据!H8 -> 15343.18 | E8: =B8+C8+D8 -> 65174.88 | F8: =B8/毛利分析!B8 -> 0.072545498 | G8: =C8/毛利分析!B8 -> 0.10224827 | H8: =E8/毛利分析!B8 -> 0.22861277 | I8: =E8/E7-1 -> -0.66439561 | J8: =SUM(E$5:E8) -> 741886.26
A9: 5 | B9: =月度数据!I9 -> 67340.15 | C9: =月度数据!J9 -> 106940.62 | D9: =月度数据!H9 -> 55142.97 | E9: =B9+C9+D9 -> 229423.74 | F9: =B9/毛利分析!B9 -> 0.06266189 | G9: =C9/毛利分析!B9 -> 0.099511233 | H9: =E9/毛利分析!B9 -> 0.2134852 | I9: =E9/E8-1 -> 2.5201252 | J9: =SUM(E$5:E9) -> 971310
A10: 6 | B10: =月度数据!I10 -> 63070.73 | C10: =月度数据!J10 -> 118690.07 | D10: =月度数据!H10 -> 42559.01 | E10: =B10+C10+D10 -> 224319.81 | F10: =B10/毛利分析!B10 -> 0.058850425 | G10: =C10/毛利分析!B10 -> 0.11074806 | H10: =E10/毛利分析!B10 -> 0.20930971 | I10: =E10/E9-1 -> -0.022246739 | J10: =SUM(E$5:E10) -> 1195629.8
A11: 7 | B11: =月度数据!I11 -> 32744.03 | C11: =月度数据!J11 -> 48516.44 | D11: =月度数据!H11 -> 19503.16 | E11: =B11+C11+D11 -> 100763.63 | F11: =B11/毛利分析!B11 -> 0.060180596 | G11: =C11/毛利分析!B11 -> 0.089168874 | H11: =E11/毛利分析!B11 -> 0.18519453 | I11: =E11/E10-1 -> -0.55080369 | J11: =SUM(E$5:E11) -> 1296393.4
A12: 8 | B12: =月度数据!I12 -> 65180.03 | C12: =月度数据!J12 -> 91385.21 | D12: =月度数据!H12 -> 29000.92 | E12: =B12+C12+D12 -> 185566.16 | F12: =B12/毛利分析!B12 -> 0.074357846 | G12: =C12/毛利分析!B12 -> 0.1042529 | H12: =E12/毛利分析!B12 -> 0.21169521 | I12: =E12/E11-1 -> 0.8415986 | J12: =SUM(E$5:E12) -> 1481959.6
A13: 9 | B13: =月度数据!I13 -> 30189.93 | C13: =月度数据!J13 -> 40359.67 | D13: =月度数据!H13 -> 30219.33 | E13: =B13+C13+D13 -> 100768.93 | F13: =B13/毛利分析!B13 -> 0.051142259 | G13: =C13/毛利分析!B13 -> 0.068369973 | H13: =E13/毛利分析!B13 -> 0.17070429 | I13: =E13/E12-1 -> -0.45696494 | J13: =SUM(E$5:E13) -> 1582728.5
A14: 10 | B14: =月度数据!I14 -> 40399.2 | C14: =月度数据!J14 -> 76687.24 | D14: =月度数据!H14 -> 31899.98 | E14: =B14+C14+D14 -> 148986.42 | F14: =B14/毛利分析!B14 -> 0.059770861 | G14: =C14/毛利分析!B14 -> 0.11345924 | H14: =E14/毛利分析!B14 -> 0.22042631 | I14: =E14/E13-1 -> 0.4784956 | J14: =SUM(E$5:E14) -> 1731714.9
A15: 11 | B15: =月度数据!I15 -> 138263.59 | C15: =月度数据!J15 -> 117506.71 | D15: =月度数据!H15 -> 68541.69 | E15: =B15+C15+D15 -> 324311.99 | F15: =B15/毛利分析!B15 -> 0.087342672 | G15: =C15/毛利分析!B15 -> 0.074230317 | H15: =E15/毛利分析!B15 -> 0.20487155 | I15: =E15/E14-1 -> 1.1767889 | J15: =SUM(E$5:E15) -> 2056026.9
A16: 12 | B16: =月度数据!I16 -> 20067.96 | C16: =月度数据!J16 -> 15751.22 | D16: =月度数据!H16 -> 9022.21 | E16: =B16+C16+D16 -> 44841.39 | F16: =B16/毛利分析!B16 -> 0.083756555 | G16: =C16/毛利分析!B16 -> 0.065740012 | H16: =E16/毛利分析!B16 -> 0.18715207 | I16: =E16/E15-1 -> -0.86173379 | J16: =SUM(E$5:E16) -> 2100868.3
A17: 合计/全年 | B17: =SUM(B5:B16) -> 699880.1 | C17: =SUM(C5:C16) -> 935858.16 | D17: =SUM(D5:D16) -> 465130.07 | E17: =SUM(E5:E16) -> 2100868.3 | F17: =C17/B17 -> 1.3371693 | G17: =C17/毛利分析!B17 -> 0.093538992 | H17: =E17/毛利分析!B17 -> 0.20998172 | J17: =SUM(E5:E16) -> 2100868.3

Sheet 预算对比
A4: 月份 | B4: 预算收入 | C4: 实际收入 | D4: 收入差异 | E4: 预算毛利 | F4: 实际毛利 | G4: 毛利差异 | H4: 收入达成率 | I4: 毛利达成率 | J4: 达成标记 | K4: 差异率
A5: 1 | B5: 931616.66 | C5: =毛利分析!B5 -> 958329.9 | D5: =C5-B5 -> 26713.24 | E5: 199286.16 | F5: =毛利分析!D5 -> 176777.22 | G5: =F5-E5 -> -22508.94 | H5: =C5/B5 -> 1.0286741 | I5: =F5/E5 -> 0.88705217 | J5: =IF(H5>=1,"达成","未达成") -> 达成 | K5: =D5/B5 -> 0.028674069
A6: 2 | B6: 1210874.5 | C6: =毛利分析!B6 -> 1334870.7 | D6: =C6-B6 -> 123996.13 | E6: 273976.01 | F6: =毛利分析!D6 -> 272146.26 | G6: =F6-E6 -> -1829.75 | H6: =C6/B6 -> 1.1024021 | I6: =F6/E6 -> 0.9933215 | J6: =IF(H6>=1,"达成","未达成") -> 达成 | K6: =D6/B6 -> 0.10240213
A7: 3 | B7: 790050.99 | C7: =毛利分析!B7 -> 770862.73 | D7: =C7-B7 -> -19188.26 | E7: 166134 | F7: =毛利分析!D7 -> 183009.35 | G7: =F7-E7 -> 16875.35 | H7: =C7/B7 -> 0.97571263 | I7: =F7/E7 -> 1.1015767 | J7: =IF(H7>=1,"达成","未达成") -> 未达成 | K7: =D7/B7 -> -0.024287369
A8: 4 | B8: 251487.97 | C8: =毛利分析!B8 -> 285088.54 | D8: =C8-B8 -> 33600.57 | E8: 63203.7 | F8: =毛利分析!D8 -> 58323.41 | G8: =F8-E8 -> -4880.29 | H8: =C8/B8 -> 1.1336071 | I8: =F8/E8 -> 0.92278474 | J8: =IF(H8>=1,"达成","未达成") -> 达成 | K8: =D8/B8 -> 0.13360707
A9: 5 | B9: 1007513.9 | C9: =毛利分析!B9 -> 1074658.8 | D9: =C9-B9 -> 67144.88 | E9: 303840.38 | F9: =毛利分析!D9 -> 275748.7 | G9: =F9-E9 -> -28091.68 | H9: =C9/B9 -> 1.0666441 | I9: =F9/E9 -> 0.90754461 | J9: =IF(H9>=1,"达成","未达成") -> 达成 | K9: =D9/B9 -> 0.066644123
A10: 6 | B10: 1036689.2 | C10: =毛利分析!B10 -> 1071712.4 | D10: =C10-B10 -> 35023.23 | E10: 364151.41 | F10: =毛利分析!D10 -> 333612.02 | G10: =F10-E10 -> -30539.39 | H10: =C10/B10 -> 1.0337837 | I10: =F10/E10 -> 0.91613546 | J10: =IF(H10>=1,"达成","未达成") -> 达成 | K10: =D10/B10 -> 0.033783733
A11: 7 | B11: 613136.51 | C11: =毛利分析!B11 -> 544096.14 | D11: =C11-B11 -> -69040.37 | E11: 120725.89 | F11: =毛利分析!D11 -> 126264.06 | G11: =F11-E11 -> 5538.17 | H11: =C11/B11 -> 0.88739804 | I11: =F11/E11 -> 1.0458739 | J11: =IF(H11>=1,"达成","未达成") -> 未达成 | K11: =D11/B11 -> -0.11260196
A12: 8 | B12: 754261.61 | C12: =毛利分析!B12 -> 876572.32 | D12: =C12-B12 -> 122310.71 | E12: 225699.35 | F12: =毛利分析!D12 -> 235034.31 | G12: =F12-E12 -> 9334.96 | H12: =C12/B12 -> 1.1621595 | I12: =F12/E12 -> 1.0413602 | J12: =IF(H12>=1,"达成","未达成") -> 达成 | K12: =D12/B12 -> 0.16215953
A13: 9 | B13: 561725.3 | C13: =毛利分析!B13 -> 590312.8 | D13: =C13-B13 -> 28587.5 | E13: 159996.26 | F13: =毛利分析!D13 -> 147120.73 | G13: =F13-E13 -> -12875.53 | H13: =C13/B13 -> 1.0508923 | I13: =F13/E13 -> 0.91952606 | J13: =IF(H13>=1,"达成","未达成") -> 达成 | K13: =D13/B13 -> 0.050892313
A14: 10 | B14: 712558.52 | C14: =毛利分析!B14 -> 675901.26 | D14: =C14-B14 -> -36657.26 | E14: 159159.78 | F14: =毛利分析!D14 -> 157972.52 | G14: =F14-E14 -> -1187.26 | H14: =C14/B14 -> 0.94855544 | I14: =F14/E14 -> 0.99254045 | J14: =IF(H14>=1,"达成","未达成") -> 未达成 | K14: =D14/B14 -> -0.051444561
A15: 11 | B15: 1767045 | C15: =毛利分析!B15 -> 1583001.6 | D15: =C15-B15 -> -184043.4 | E15: 462475.22 | F15: =毛利分析!D15 -> 483642.22 | G15: =F15-E15 -> 21167 | H15: =C15/B15 -> 0.8958468 | I15: =F15/E15 -> 1.0457689 | J15: =IF(H15>=1,"达成","未达成") -> 未达成 | K15: =D15/B15 -> -0.1041532
A16: 12 | B16: 248958.34 | C16: =毛利分析!B16 -> 239598.68 | D16: =C16-B16 -> -9359.66 | E16: 69028.48 | F16: =毛利分析!D16 -> 62624.55 | G16: =F16-E16 -> -6403.93 | H16: =C16/B16 -> 0.96240471 | I16: =F16/E16 -> 0.90722771 | J16: =IF(H16>=1,"达成","未达成") -> 未达成 | K16: =D16/B16 -> -0.037595286
A17: 合计/全年 | B17: =SUM(B5:B16) -> 9885918.5 | C17: =SUM(C5:C16) -> 10005006 | D17: =B17-C17 -> -119087.31 | E17: =SUM(E5:E16) -> 2567676.6 | F17: =SUM(F5:F16) -> 2512275.4 | G17: =F17-E17 -> -55401.29 | H17: =C17/B17 -> 1.0120462 | I17: =F17/E17 -> 0.97842357 | K17: =D17/B17 -> -0.012046155
A18: 达标月数 | B18: =COUNTIF(J5:J16,"未达成") -> 5

Sheet 校验
A1: 模型查错校验表（部分检查按设计应为 FALSE——请定位原因）
A3: 编号 | B3: 校验项 | C3: 结果 | D3: 说明
A4: 1 | B4: 收入合计一致 | C4: =ABS(毛利分析!B17-SUM(月度数据!D5:D16))<0.01 -> TRUE | D4: 毛利分析表全年收入应等于月度数据收入列合计
A5: 2 | B5: 变动成本合计一致 | C5: =ABS(毛利分析!C17-SUM(月度数据!E5:H16))<0.01 -> TRUE | D5: 变动成本=原材料+人工+制造费用+运输费用
A6: 3 | B6: 毛利恒等式 | C6: =ABS(毛利分析!D17-(毛利分析!B17-毛利分析!C17))<0.01 -> TRUE | D6: 全年毛利=收入-变动成本
A7: 4 | B7: 累计收入期末=全年收入 | C7: =ABS(毛利分析!J16-毛利分析!B17)<0.01 -> FALSE | D7: 12月累计收入列应等于全年收入合计
A8: 5 | B8: 单位毛利勾稽 | C8: =ABS(毛利分析!F17-(毛利分析!B17/SUM(月度数据!B5:B16)-毛利分析!G17))<0.0001 -> FALSE | D8: 全年单位毛利=全年单位售价-全年单位成本
A9: 6 | B9: 全年销售费用率 | C9: =ABS(费用分析!F17-费用分析!B17/毛利分析!B17)<0.0001 -> FALSE | D9: 全年销售费用率=销售费用合计/全年收入
A10: 7 | B10: 累计毛利期末=全年毛利 | C10: =ABS(毛利分析!K16-毛利分析!D17)<0.01 -> FALSE | D10: 12月累计毛利列应等于全年毛利合计
A11: 8 | B11: 全年收入差异方向 | C11: =ABS(预算对比!D17-(预算对比!C17-预算对比!B17))<0.01 -> FALSE | D11: 收入差异=实际-预算
A12: 9 | B12: 全年毛利率恒等式 | C12: =ABS(毛利分析!E17-(1-毛利分析!C17/毛利分析!B17))<0.0001 -> TRUE | D12: 毛利率=1-变动成本率
A13: 10 | B13: 累计毛利率期末=全年毛利率 | C13: =ABS(毛利分析!H16-毛利分析!E17)<0.0005 -> FALSE | D13: 12月累计毛利率应等于全年毛利率
A14: 11 | B14: 2月收入环比口径 | C14: =ABS(毛利分析!I6-(月度数据!D6/月度数据!D5-1))<0.0001 -> FALSE | D14: 2月环比=2月收入/1月收入-1
A15: 12 | B15: 达标月数统计 | C15: =COUNTIF(预算对比!J5:J16,"达成")=预算对比!B18 -> FALSE | D15: 达标月数应等于标记为「达成」的月份数
A17: 总判定 | B17: =AND(C4:C15) -> FALSE
A18: 通过数 | B18: =COUNTIF(C4:C15,TRUE) -> 4
A19: 未通过数 | B19: =COUNTIF(C4:C15,FALSE) -> 8
